{
  "title": "3 Bizarre Facts About Sleep",
  "segments": [
    {
      "text": "You can't actually 'catch up' on lost sleep.",
      "keywords": "sleeping person"
    },
    {
      "text": "But wait, that’s just the start.",
      "keywords": "sleep biology"
    },
    {
      "text": "Sleep deprivation affects your memory and emotions.",
      "keywords": "memory sleep"
    },
    {
      "text": "And most dreaming happens in REM sleep.",
      "keywords": "REM sleep"
    },
    {
      "text": "Is your sleep routine doing you any favors?",
      "keywords": "sleep habits"
    },
    {
      "text": "Follow for more facts that sound fake but are real.",
      "keywords": "sleep facts"
    }
  ],
  "description": "Get ready for some bizarre sleep facts! Follow for daily facts! 😴",
  "hashtags": [
    "#sleep",
    "#facts",
    "#health",
    "#curiosity",
    "#shorts",
    "#fyp",
    "#wellness"
  ]
}