{
  "title": "3 Fascinating Facts About The Ocean",
  "segments": [
    {
      "text": "We know more about outer space than our oceans.",
      "keywords": "ocean depth"
    },
    {
      "text": "But there's so much more to explore.",
      "keywords": "exploring the ocean"
    },
    {
      "text": "Over 80% of the ocean is unexplored and unmapped.",
      "keywords": "unexplored ocean"
    },
    {
      "text": "And some deep-sea creatures are bioluminescent!",
      "keywords": "bioluminescent creature"
    },
    {
      "text": "What's hiding in the ocean's depths?",
      "keywords": "ocean mystery"
    },
    {
      "text": "Follow for more facts that sound fake but are real.",
      "keywords": "ocean facts"
    }
  ],
  "description": "Dive into these ocean facts that will astound you! Follow for daily facts! 🌊",
  "hashtags": [
    "#ocean",
    "#facts",
    "#nature",
    "#curiosity",
    "#shorts",
    "#fyp",
    "#marine"
  ]
}